netviz_tools/__init__.py
netviz_tools/data_manager.py
netviz_tools/trade_network.py
netviz_tools/trade_series.py
netviz_tools/utils.py
netviz_tools-2025.0.2.dist-info/licenses/LICENSE
netviz_tools-2025.0.2.dist-info/METADATA
netviz_tools-2025.0.2.dist-info/WHEEL
netviz_tools-2025.0.2.dist-info/top_level.txt
netviz_tools-2025.0.2.dist-info/RECORD
