Metadata-Version: 2.4
Name: netviz_tools
Version: 2025.0.2
Summary: Network-visualization toolkit for analyzing and visualizing complex networks.
Author-email: Tyson Johnson <tjohns94@gmu.edu>
License-Expression: MIT
Requires-Python: >=3.13
License-File: LICENSE
Requires-Dist: pandas
Requires-Dist: numpy
Requires-Dist: networkx
Requires-Dist: matplotlib
Requires-Dist: geopandas
Requires-Dist: plotly
Requires-Dist: pygraphviz
Requires-Dist: powerlaw
Provides-Extra: dev
Requires-Dist: pytest>=6.0; extra == "dev"
Dynamic: license-file
